git_speed/__init__.py
git_speed/cli.py
git_speed/git_aliases
git_speed/installer.py
git_speed-1.1.1.dist-info/entry_points.txt
git_speed-1.1.1.dist-info/LICENSE
git_speed-1.1.1.dist-info/WHEEL
git_speed-1.1.1.dist-info/METADATA
git_speed-1.1.1.dist-info/RECORD
