Metadata-Version: 2.1
Name: git-speed
Version: 1.1.1
Summary: Installs Git aliases.
Home-page: https://www.gitscientist.com
License: MIT
Author: Daniel Tipping
Author-email: daniel@gitscientist.com
Requires-Python: >=3.6,<4.0
Classifier: License :: OSI Approved :: MIT License
Classifier: Programming Language :: Python :: 3
Classifier: Programming Language :: Python :: 3.6
Classifier: Programming Language :: Python :: 3.7
Classifier: Programming Language :: Python :: 3.8
Classifier: Programming Language :: Python :: 3.9
Requires-Dist: typer (>=0.1.1,<0.2.0)
Project-URL: Repository, https://github.com/git-scientist/git-speed
